s3multipart/__init__.py
s3multipart/cli.py
s3multipart-0.1.0.dist-info/entry_points.txt
s3multipart-0.1.0.dist-info/LICENSE.md
s3multipart-0.1.0.dist-info/WHEEL
s3multipart-0.1.0.dist-info/METADATA
s3multipart-0.1.0.dist-info/RECORD
