Metadata-Version: 2.1
Name: s3multipart
Version: 0.1.0
Summary: 
Home-page: UNKNOWN
License: UNKNOWN
Author: davido-bs
Author-email: david.oliver@strategic-i.com
Requires-Python: >=3.6,<4.0
Classifier: Programming Language :: Python :: 3
Classifier: Programming Language :: Python :: 3.6
Classifier: Programming Language :: Python :: 3.7
Requires-Dist: boto3 (>=1.9,<2.0)
Requires-Dist: click (>=7.0,<8.0)
